{
	"root": false,
	"$schema": "https://biomejs.dev/schemas/2.4.15/schema.json",
	"extends": "//",
	"files": {
		"includes": ["src/**/*.ts", "src/**/*.tsx", "src/**/*.js", "*.json"],
		"ignoreUnknown": true
	},
	"linter": {
		"rules": {
			"style": {
				"useFilenamingConvention": "off"
			},
			"a11y": {
				"useSemanticElements": "off",
				"useFocusableInteractive": "off",
				"useKeyWithClickEvents": "off",
				"useAriaPropsForRole": "off",
				"noRedundantRoles": "off"
			},
			"correctness": {
				"useExhaustiveDependencies": "off"
			},
			"suspicious": {
				"noArrayIndexKey": "off",
				"noDoubleEquals": "off",
				"noDocumentCookie": "off"
			},
			"security": {
				"noDangerouslySetInnerHtml": "off"
			}
		}
	}
}
